cbvhtmx/__init__.py
cbvhtmx/apps.py
cbvhtmx/form_widgets.py
cbvhtmx/mixins.py
cbvhtmx/models.py
cbvhtmx/services.py
cbvhtmx/tests.py
cbvhtmx/tools.py
cbvhtmx/migrations/__init__.py
cbvhtmx/templatetags/__init__.py
cbvhtmx/templatetags/query_extras.py
django_cbv_htmx-0.0.5.dist-info/LICENSE
django_cbv_htmx-0.0.5.dist-info/METADATA
django_cbv_htmx-0.0.5.dist-info/WHEEL
django_cbv_htmx-0.0.5.dist-info/top_level.txt
django_cbv_htmx-0.0.5.dist-info/RECORD
